MC23152UNO/__init__.py
MC23152UNO/metodos.py
MC23152UNO-0.1.0.dist-info/LICENSE
MC23152UNO-0.1.0.dist-info/METADATA
MC23152UNO-0.1.0.dist-info/WHEEL
MC23152UNO-0.1.0.dist-info/top_level.txt
MC23152UNO-0.1.0.dist-info/RECORD
