Metadata-Version: 2.1
Name: MC23152UNO
Version: 0.1.0
Summary: Librería de métodos numéricos para resolver sistemas de ecuaciones (lineales y no lineales)
Home-page: https://github.com/moisescorado91
Author: Moises Isaac Molina Corado
Author-email: mc23512@ues.edu.sv
Classifier: Programming Language :: Python :: 3
Classifier: License :: OSI Approved :: MIT License
Classifier: Operating System :: OS Independent
Requires-Python: >=3.6
License-File: LICENSE
Requires-Dist: numpy>=1.19.0
